audio_recorder_streamlit/__init__.py
audio_recorder_streamlit/frontend/build/asset-manifest.json
audio_recorder_streamlit/frontend/build/bootstrap.min.css
audio_recorder_streamlit/frontend/build/index.html
audio_recorder_streamlit/frontend/build/precache-manifest.09802b9861500bec69511c0bdb7ba24e.js
audio_recorder_streamlit/frontend/build/precache-manifest.2db2d11f16ada34d62ec22b5b0cec05a.js
audio_recorder_streamlit/frontend/build/precache-manifest.33565d3861a370f5dacdf5cf248fd17c.js
audio_recorder_streamlit/frontend/build/precache-manifest.4d7c73efb4715bff4fa44233cbb15e02.js
audio_recorder_streamlit/frontend/build/precache-manifest.59c50058ffb6e1efa45f44fa583380aa.js
audio_recorder_streamlit/frontend/build/precache-manifest.7b37fbe5ae5bdf9e7a096a2941434619.js
audio_recorder_streamlit/frontend/build/precache-manifest.9782521dd2c7c4990547108294100a4e.js
audio_recorder_streamlit/frontend/build/precache-manifest.99a81c714bc289212810fda910490c29.js
audio_recorder_streamlit/frontend/build/precache-manifest.9d1c95943d752dd861b901ad3474449b.js
audio_recorder_streamlit/frontend/build/precache-manifest.a1debe2658acc658860ceebf46a68343.js
audio_recorder_streamlit/frontend/build/precache-manifest.ac29a01f8f4da215208cd02f0cfce545.js
audio_recorder_streamlit/frontend/build/precache-manifest.bb291740c502512d4e4c150cd71a7fc7.js
audio_recorder_streamlit/frontend/build/precache-manifest.c435486cdc678a0e50e91db6ee3c2876.js
audio_recorder_streamlit/frontend/build/precache-manifest.ffed8f59c2ace01163157da6280b3ed3.js
audio_recorder_streamlit/frontend/build/service-worker.js
audio_recorder_streamlit/frontend/build/static/js/2.12accc2a.chunk.js
audio_recorder_streamlit/frontend/build/static/js/2.12accc2a.chunk.js.LICENSE.txt
audio_recorder_streamlit/frontend/build/static/js/2.12accc2a.chunk.js.map
audio_recorder_streamlit/frontend/build/static/js/main.2e219f5f.chunk.js
audio_recorder_streamlit/frontend/build/static/js/main.2e219f5f.chunk.js.map
audio_recorder_streamlit_auto-0.0.1.dist-info/LICENSE
audio_recorder_streamlit_auto-0.0.1.dist-info/METADATA
audio_recorder_streamlit_auto-0.0.1.dist-info/WHEEL
audio_recorder_streamlit_auto-0.0.1.dist-info/top_level.txt
audio_recorder_streamlit_auto-0.0.1.dist-info/RECORD
