Metadata-Version: 2.1
Name: audio-recorder-streamlit-auto
Version: 0.0.1
Home-page: https://github.com/misterkevinski/audio-recorder-streamlit
Author: Kevin Beck
Author-email: misterkevinski@gmail.com
Requires-Python: >=3.8
License-File: LICENSE
Requires-Dist: streamlit>=0.63
